arabic_ocr_online/__init__.py
arabic_ocr_online/arabic_ocr_online.py
arabic_ocr_online-1.7.dist-info/METADATA
arabic_ocr_online-1.7.dist-info/WHEEL
arabic_ocr_online-1.7.dist-info/top_level.txt
arabic_ocr_online-1.7.dist-info/RECORD
