Metadata-Version: 2.1
Name: arabic_ocr_online
Version: 1.7
Requires-Dist: easyocr >=1.7.1
Requires-Dist: numpy >=1.26.4
Requires-Dist: requests >=2.32.2
Requires-Dist: opencv-python >=4.9.0.80
